scilicet/__init__.py
scilicet/core.py
scilicet/guesser.py
scilicet/repo.py
scilicet/text.py
scilicet-0.2.dist-info/METADATA
scilicet-0.2.dist-info/RECORD
scilicet-0.2.dist-info/WHEEL
scilicet-0.2.dist-info/entry_points.txt
scilicet-0.2.dist-info/top_level.txt
